pyboost/main.py
pyboost_auditor-0.2.2.dist-info/licenses/LICENSE
pyboost_auditor-0.2.2.dist-info/METADATA
pyboost_auditor-0.2.2.dist-info/WHEEL
pyboost_auditor-0.2.2.dist-info/entry_points.txt
pyboost_auditor-0.2.2.dist-info/top_level.txt
pyboost_auditor-0.2.2.dist-info/RECORD
