Metadata-Version: 2.4
Name: pyboost-auditor
Version: 0.2.2
Summary: An upgrade assistant to audit Python projects and estimate cloud cost savings.
Author-email: Anoop Johny <anoopjohny@gmail.com>
License: MIT
Classifier: Programming Language :: Python :: 3
Classifier: License :: OSI Approved :: MIT License
Classifier: Operating System :: OS Independent
Classifier: Topic :: Software Development :: Build Tools
Classifier: Topic :: System :: Systems Administration
Requires-Python: >=3.8
License-File: LICENSE
Requires-Dist: rich>=13.0.0
Dynamic: license-file
